lytics_api_wrapper/__init__.py
lytics_api_wrapper/wrapper.py
lytics_api_wrapper-0.0.4.dist-info/METADATA
lytics_api_wrapper-0.0.4.dist-info/WHEEL
lytics_api_wrapper-0.0.4.dist-info/licenses/LICENSE
lytics_api_wrapper-0.0.4.dist-info/RECORD
