Metadata-Version: 2.1
Name: lytics_api_wrapper
Version: 0.0.4
Summary: A python class wrapper around the Lytics API
Project-URL: Homepage, https://github.com/tandreason/lytics-api-wrapper
Project-URL: Bug Tracker, https://github.com/tandreason/lytics-api-wrapper/issues
Author-email: Trace Andreason <tandreason@gmail.com>
License: MIT License
License-File: LICENSE
Classifier: License :: OSI Approved :: MIT License
Classifier: Operating System :: OS Independent
Classifier: Programming Language :: Python :: 3
Requires-Python: >=3.7
